banpei/__init__.py
banpei/base/__init__.py
banpei/base/model.py
banpei/hotelling.py
banpei/sst.py
banpei/utils.py
banpei-0.1.2.dist-info/LICENSE
banpei-0.1.2.dist-info/WHEEL
banpei-0.1.2.dist-info/METADATA
banpei-0.1.2.dist-info/RECORD
